{
    "info": {
        "year": "",
        "version": "1",
        "description": "",
        "contributor": "",
        "url": "",
        "date_created": ""
    },
    "licenses": [],
    "categories": [
        {
            "id": 0,
            "name": "Abstract",
            "supercategory": ""
        },
        {
            "id": 1,
            "name": "Author",
            "supercategory": ""
        },
        {
            "id": 2,
            "name": "Caption",
            "supercategory": ""
        },
        {
            "id": 3,
            "name": "Equation",
            "supercategory": ""
        },
        {
            "id": 4,
            "name": "Figure",
            "supercategory": ""
        },
        {
            "id": 5,
            "name": "Footer",
            "supercategory": ""
        },
        {
            "id": 6,
            "name": "List",
            "supercategory": ""
        },
        {
            "id": 7,
            "name": "Paragraph",
            "supercategory": ""
        },
        {
            "id": 8,
            "name": "Reference",
            "supercategory": ""
        },
        {
            "id": 9,
            "name": "Section",
            "supercategory": ""
        },
        {
            "id": 10,
            "name": "Table",
            "supercategory": ""
        },
        {
            "id": 11,
            "name": "Title",
            "supercategory": ""
        },
        {
            "id": 12,
            "name": "Date",
            "supercategory": ""
        }
    ],
    "images": [
        {
            "id": 39,
            "license": "",
            "file_name": "173.tar_1708.02244.gz_D1D5BPSv2_39.jpg",
            "height": "",
            "width": "",
            "date_captured": ""
        }
    ],
    "annotations": [
        {
            "id": 29800,
            "image_id": 39,
            "iscrowd": 0,
            "segmentation": [],
            "category_id": 3,
            "bbox": [
                474,
                86,
                12,
                47
            ],
            "area": 564
        },
        {
            "id": 29801,
            "image_id": 39,
            "iscrowd": 0,
            "segmentation": [],
            "category_id": 3,
            "bbox": [
                642,
                86,
                12,
                47
            ],
            "area": 564
        },
        {
            "id": 29802,
            "image_id": 39,
            "iscrowd": 0,
            "segmentation": [],
            "category_id": 3,
            "bbox": [
                163,
                92,
                23,
                47
            ],
            "area": 1081
        },
        {
            "id": 29803,
            "image_id": 39,
            "iscrowd": 0,
            "segmentation": [],
            "category_id": 3,
            "bbox": [
                663,
                92,
                21,
                47
            ],
            "area": 987
        },
        {
            "id": 29804,
            "image_id": 39,
            "iscrowd": 0,
            "segmentation": [],
            "category_id": 3,
            "bbox": [
                506,
                115,
                13,
                22
            ],
            "area": 286
        },
        {
            "id": 29805,
            "image_id": 39,
            "iscrowd": 0,
            "segmentation": [],
            "category_id": 3,
            "bbox": [
                194,
                124,
                13,
                21
            ],
            "area": 273
        },
        {
            "id": 29806,
            "image_id": 39,
            "iscrowd": 0,
            "segmentation": [],
            "category_id": 3,
            "bbox": [
                353,
                124,
                12,
                21
            ],
            "area": 252
        },
        {
            "id": 29807,
            "image_id": 39,
            "iscrowd": 0,
            "segmentation": [],
            "category_id": 3,
            "bbox": [
                377,
                124,
                11,
                16
            ],
            "area": 176
        },
        {
            "id": 29808,
            "image_id": 39,
            "iscrowd": 0,
            "segmentation": [],
            "category_id": 3,
            "bbox": [
                435,
                124,
                11,
                16
            ],
            "area": 176
        },
        {
            "id": 29809,
            "image_id": 39,
            "iscrowd": 0,
            "segmentation": [],
            "category_id": 3,
            "bbox": [
                519,
                124,
                13,
                13
            ],
            "area": 169
        },
        {
            "id": 29810,
            "image_id": 39,
            "iscrowd": 0,
            "segmentation": [],
            "category_id": 3,
            "bbox": [
                540,
                124,
                18,
                13
            ],
            "area": 234
        },
        {
            "id": 29811,
            "image_id": 39,
            "iscrowd": 0,
            "segmentation": [],
            "category_id": 3,
            "bbox": [
                561,
                123,
                60,
                14
            ],
            "area": 840
        },
        {
            "id": 29812,
            "image_id": 39,
            "iscrowd": 0,
            "segmentation": [],
            "category_id": 3,
            "bbox": [
                777,
                124,
                9,
                13
            ],
            "area": 117
        },
        {
            "id": 29813,
            "image_id": 39,
            "iscrowd": 0,
            "segmentation": [],
            "category_id": 3,
            "bbox": [
                188,
                133,
                6,
                12
            ],
            "area": 72
        },
        {
            "id": 29814,
            "image_id": 39,
            "iscrowd": 0,
            "segmentation": [],
            "category_id": 3,
            "bbox": [
                207,
                131,
                43,
                14
            ],
            "area": 602
        },
        {
            "id": 29815,
            "image_id": 39,
            "iscrowd": 0,
            "segmentation": [],
            "category_id": 3,
            "bbox": [
                252,
                129,
                6,
                13
            ],
            "area": 78
        },
        {
            "id": 29816,
            "image_id": 39,
            "iscrowd": 0,
            "segmentation": [],
            "category_id": 3,
            "bbox": [
                260,
                128,
                88,
                17
            ],
            "area": 1496
        },
        {
            "id": 29817,
            "image_id": 39,
            "iscrowd": 0,
            "segmentation": [],
            "category_id": 3,
            "bbox": [
                369,
                133,
                8,
                12
            ],
            "area": 96
        },
        {
            "id": 29818,
            "image_id": 39,
            "iscrowd": 0,
            "segmentation": [],
            "category_id": 3,
            "bbox": [
                388,
                131,
                47,
                14
            ],
            "area": 658
        },
        {
            "id": 29819,
            "image_id": 39,
            "iscrowd": 0,
            "segmentation": [],
            "category_id": 3,
            "bbox": [
                446,
                131,
                5,
                9
            ],
            "area": 45
        },
        {
            "id": 29820,
            "image_id": 39,
            "iscrowd": 0,
            "segmentation": [],
            "category_id": 3,
            "bbox": [
                457,
                133,
                13,
                12
            ],
            "area": 156
        },
        {
            "id": 29821,
            "image_id": 39,
            "iscrowd": 0,
            "segmentation": [],
            "category_id": 3,
            "bbox": [
                532,
                129,
                7,
                9
            ],
            "area": 63
        },
        {
            "id": 29822,
            "image_id": 39,
            "iscrowd": 0,
            "segmentation": [],
            "category_id": 3,
            "bbox": [
                714,
                133,
                12,
                22
            ],
            "area": 264
        },
        {
            "id": 29823,
            "image_id": 39,
            "iscrowd": 0,
            "segmentation": [],
            "category_id": 3,
            "bbox": [
                780,
                137,
                3,
                11
            ],
            "area": 33
        },
        {
            "id": 29824,
            "image_id": 39,
            "iscrowd": 0,
            "segmentation": [],
            "category_id": 3,
            "bbox": [
                857,
                137,
                4,
                11
            ],
            "area": 44
        },
        {
            "id": 29825,
            "image_id": 39,
            "iscrowd": 0,
            "segmentation": [],
            "category_id": 3,
            "bbox": [
                869,
                133,
                5,
                12
            ],
            "area": 60
        },
        {
            "id": 29826,
            "image_id": 39,
            "iscrowd": 0,
            "segmentation": [],
            "category_id": 3,
            "bbox": [
                488,
                141,
                62,
                14
            ],
            "area": 868
        },
        {
            "id": 29827,
            "image_id": 39,
            "iscrowd": 0,
            "segmentation": [],
            "category_id": 3,
            "bbox": [
                553,
                141,
                69,
                13
            ],
            "area": 897
        },
        {
            "id": 29828,
            "image_id": 39,
            "iscrowd": 0,
            "segmentation": [],
            "category_id": 3,
            "bbox": [
                625,
                142,
                15,
                12
            ],
            "area": 180
        },
        {
            "id": 29829,
            "image_id": 39,
            "iscrowd": 0,
            "segmentation": [],
            "category_id": 3,
            "bbox": [
                687,
                146,
                3,
                11
            ],
            "area": 33
        },
        {
            "id": 29830,
            "image_id": 39,
            "iscrowd": 0,
            "segmentation": [],
            "category_id": 3,
            "bbox": [
                696,
                142,
                14,
                13
            ],
            "area": 182
        },
        {
            "id": 29831,
            "image_id": 39,
            "iscrowd": 0,
            "segmentation": [],
            "category_id": 3,
            "bbox": [
                730,
                142,
                50,
                13
            ],
            "area": 650
        },
        {
            "id": 29832,
            "image_id": 39,
            "iscrowd": 0,
            "segmentation": [],
            "category_id": 3,
            "bbox": [
                785,
                141,
                72,
                14
            ],
            "area": 1008
        },
        {
            "id": 29833,
            "image_id": 39,
            "iscrowd": 0,
            "segmentation": [],
            "category_id": 3,
            "bbox": [
                861,
                142,
                5,
                9
            ],
            "area": 45
        },
        {
            "id": 29834,
            "image_id": 39,
            "iscrowd": 0,
            "segmentation": [],
            "category_id": 3,
            "bbox": [
                162,
                151,
                25,
                11
            ],
            "area": 275
        },
        {
            "id": 29835,
            "image_id": 39,
            "iscrowd": 0,
            "segmentation": [],
            "category_id": 3,
            "bbox": [
                656,
                151,
                31,
                9
            ],
            "area": 279
        },
        {
            "id": 29836,
            "image_id": 39,
            "iscrowd": 0,
            "segmentation": [],
            "category_id": 3,
            "bbox": [
                792,
                169,
                45,
                13
            ],
            "area": 585
        },
        {
            "id": 29837,
            "image_id": 39,
            "iscrowd": 0,
            "segmentation": [],
            "category_id": 7,
            "bbox": [
                186,
                215,
                42,
                13
            ],
            "area": 546
        },
        {
            "id": 29838,
            "image_id": 39,
            "iscrowd": 0,
            "segmentation": [],
            "category_id": 7,
            "bbox": [
                232,
                215,
                38,
                13
            ],
            "area": 494
        },
        {
            "id": 29839,
            "image_id": 39,
            "iscrowd": 0,
            "segmentation": [],
            "category_id": 7,
            "bbox": [
                275,
                215,
                19,
                13
            ],
            "area": 247
        },
        {
            "id": 29840,
            "image_id": 39,
            "iscrowd": 0,
            "segmentation": [],
            "category_id": 7,
            "bbox": [
                298,
                215,
                33,
                13
            ],
            "area": 429
        },
        {
            "id": 29841,
            "image_id": 39,
            "iscrowd": 0,
            "segmentation": [],
            "category_id": 7,
            "bbox": [
                335,
                215,
                59,
                13
            ],
            "area": 767
        },
        {
            "id": 29842,
            "image_id": 39,
            "iscrowd": 0,
            "segmentation": [],
            "category_id": 7,
            "bbox": [
                398,
                215,
                23,
                13
            ],
            "area": 299
        },
        {
            "id": 29843,
            "image_id": 39,
            "iscrowd": 0,
            "segmentation": [],
            "category_id": 7,
            "bbox": [
                426,
                215,
                64,
                13
            ],
            "area": 832
        },
        {
            "id": 29844,
            "image_id": 39,
            "iscrowd": 0,
            "segmentation": [],
            "category_id": 7,
            "bbox": [
                495,
                215,
                13,
                13
            ],
            "area": 169
        },
        {
            "id": 29845,
            "image_id": 39,
            "iscrowd": 0,
            "segmentation": [],
            "category_id": 7,
            "bbox": [
                513,
                215,
                13,
                13
            ],
            "area": 169
        },
        {
            "id": 29846,
            "image_id": 39,
            "iscrowd": 0,
            "segmentation": [],
            "category_id": 7,
            "bbox": [
                532,
                215,
                17,
                13
            ],
            "area": 221
        },
        {
            "id": 29847,
            "image_id": 39,
            "iscrowd": 0,
            "segmentation": [],
            "category_id": 7,
            "bbox": [
                554,
                212,
                33,
                16
            ],
            "area": 528
        },
        {
            "id": 29848,
            "image_id": 39,
            "iscrowd": 0,
            "segmentation": [],
            "category_id": 7,
            "bbox": [
                593,
                215,
                14,
                13
            ],
            "area": 182
        },
        {
            "id": 29849,
            "image_id": 39,
            "iscrowd": 0,
            "segmentation": [],
            "category_id": 7,
            "bbox": [
                612,
                215,
                56,
                13
            ],
            "area": 728
        },
        {
            "id": 29850,
            "image_id": 39,
            "iscrowd": 0,
            "segmentation": [],
            "category_id": 7,
            "bbox": [
                673,
                215,
                18,
                13
            ],
            "area": 234
        },
        {
            "id": 29851,
            "image_id": 39,
            "iscrowd": 0,
            "segmentation": [],
            "category_id": 7,
            "bbox": [
                696,
                215,
                32,
                13
            ],
            "area": 416
        },
        {
            "id": 29852,
            "image_id": 39,
            "iscrowd": 0,
            "segmentation": [],
            "category_id": 7,
            "bbox": [
                733,
                215,
                39,
                13
            ],
            "area": 507
        },
        {
            "id": 29853,
            "image_id": 39,
            "iscrowd": 0,
            "segmentation": [],
            "category_id": 7,
            "bbox": [
                777,
                215,
                22,
                13
            ],
            "area": 286
        },
        {
            "id": 29854,
            "image_id": 39,
            "iscrowd": 0,
            "segmentation": [],
            "category_id": 7,
            "bbox": [
                804,
                215,
                33,
                13
            ],
            "area": 429
        },
        {
            "id": 29855,
            "image_id": 39,
            "iscrowd": 0,
            "segmentation": [],
            "category_id": 7,
            "bbox": [
                200,
                227,
                16,
                22
            ],
            "area": 352
        },
        {
            "id": 29856,
            "image_id": 39,
            "iscrowd": 0,
            "segmentation": [],
            "category_id": 7,
            "bbox": [
                220,
                227,
                17,
                22
            ],
            "area": 374
        },
        {
            "id": 29857,
            "image_id": 39,
            "iscrowd": 0,
            "segmentation": [],
            "category_id": 7,
            "bbox": [
                162,
                237,
                13,
                12
            ],
            "area": 156
        },
        {
            "id": 29858,
            "image_id": 39,
            "iscrowd": 0,
            "segmentation": [],
            "category_id": 7,
            "bbox": [
                180,
                237,
                13,
                12
            ],
            "area": 156
        },
        {
            "id": 29859,
            "image_id": 39,
            "iscrowd": 0,
            "segmentation": [],
            "category_id": 7,
            "bbox": [
                237,
                237,
                4,
                12
            ],
            "area": 48
        },
        {
            "id": 29860,
            "image_id": 39,
            "iscrowd": 0,
            "segmentation": [],
            "category_id": 7,
            "bbox": [
                247,
                237,
                26,
                12
            ],
            "area": 312
        },
        {
            "id": 29861,
            "image_id": 39,
            "iscrowd": 0,
            "segmentation": [],
            "category_id": 7,
            "bbox": [
                278,
                237,
                19,
                12
            ],
            "area": 228
        },
        {
            "id": 29862,
            "image_id": 39,
            "iscrowd": 0,
            "segmentation": [],
            "category_id": 7,
            "bbox": [
                302,
                237,
                42,
                12
            ],
            "area": 504
        },
        {
            "id": 29863,
            "image_id": 39,
            "iscrowd": 0,
            "segmentation": [],
            "category_id": 3,
            "bbox": [
                187,
                255,
                24,
                47
            ],
            "area": 1128
        },
        {
            "id": 29864,
            "image_id": 39,
            "iscrowd": 0,
            "segmentation": [],
            "category_id": 3,
            "bbox": [
                303,
                288,
                3,
                15
            ],
            "area": 45
        },
        {
            "id": 29865,
            "image_id": 39,
            "iscrowd": 0,
            "segmentation": [],
            "category_id": 3,
            "bbox": [
                363,
                288,
                4,
                11
            ],
            "area": 44
        },
        {
            "id": 29866,
            "image_id": 39,
            "iscrowd": 0,
            "segmentation": [],
            "category_id": 3,
            "bbox": [
                443,
                288,
                11,
                15
            ],
            "area": 165
        },
        {
            "id": 29867,
            "image_id": 39,
            "iscrowd": 0,
            "segmentation": [],
            "category_id": 3,
            "bbox": [
                518,
                287,
                13,
                22
            ],
            "area": 286
        },
        {
            "id": 29868,
            "image_id": 39,
            "iscrowd": 0,
            "segmentation": [],
            "category_id": 3,
            "bbox": [
                553,
                287,
                12,
                22
            ],
            "area": 264
        },
        {
            "id": 29869,
            "image_id": 39,
            "iscrowd": 0,
            "segmentation": [],
            "category_id": 3,
            "bbox": [
                586,
                288,
                11,
                15
            ],
            "area": 165
        },
        {
            "id": 29870,
            "image_id": 39,
            "iscrowd": 0,
            "segmentation": [],
            "category_id": 3,
            "bbox": [
                633,
                288,
                10,
                15
            ],
            "area": 150
        },
        {
            "id": 29871,
            "image_id": 39,
            "iscrowd": 0,
            "segmentation": [],
            "category_id": 3,
            "bbox": [
                661,
                287,
                13,
                22
            ],
            "area": 286
        },
        {
            "id": 29872,
            "image_id": 39,
            "iscrowd": 0,
            "segmentation": [],
            "category_id": 3,
            "bbox": [
                219,
                294,
                60,
                15
            ],
            "area": 900
        },
        {
            "id": 29873,
            "image_id": 39,
            "iscrowd": 0,
            "segmentation": [],
            "category_id": 3,
            "bbox": [
                282,
                296,
                11,
                13
            ],
            "area": 143
        },
        {
            "id": 29874,
            "image_id": 39,
            "iscrowd": 0,
            "segmentation": [],
            "category_id": 3,
            "bbox": [
                296,
                296,
                7,
                13
            ],
            "area": 91
        },
        {
            "id": 29875,
            "image_id": 39,
            "iscrowd": 0,
            "segmentation": [],
            "category_id": 3,
            "bbox": [
                307,
                294,
                56,
                15
            ],
            "area": 840
        },
        {
            "id": 29876,
            "image_id": 39,
            "iscrowd": 0,
            "segmentation": [],
            "category_id": 3,
            "bbox": [
                373,
                296,
                13,
                13
            ],
            "area": 169
        },
        {
            "id": 29877,
            "image_id": 39,
            "iscrowd": 0,
            "segmentation": [],
            "category_id": 3,
            "bbox": [
                390,
                294,
                53,
                15
            ],
            "area": 795
        },
        {
            "id": 29878,
            "image_id": 39,
            "iscrowd": 0,
            "segmentation": [],
            "category_id": 3,
            "bbox": [
                454,
                294,
                11,
                15
            ],
            "area": 165
        },
        {
            "id": 29879,
            "image_id": 39,
            "iscrowd": 0,
            "segmentation": [],
            "category_id": 3,
            "bbox": [
                468,
                296,
                13,
                13
            ],
            "area": 169
        },
        {
            "id": 29880,
            "image_id": 39,
            "iscrowd": 0,
            "segmentation": [],
            "category_id": 3,
            "bbox": [
                483,
                296,
                13,
                13
            ],
            "area": 169
        },
        {
            "id": 29881,
            "image_id": 39,
            "iscrowd": 0,
            "segmentation": [],
            "category_id": 3,
            "bbox": [
                499,
                296,
                16,
                13
            ],
            "area": 208
        },
        {
            "id": 29882,
            "image_id": 39,
            "iscrowd": 0,
            "segmentation": [],
            "category_id": 3,
            "bbox": [
                535,
                296,
                14,
                13
            ],
            "area": 182
        },
        {
            "id": 29883,
            "image_id": 39,
            "iscrowd": 0,
            "segmentation": [],
            "category_id": 3,
            "bbox": [
                569,
                296,
                17,
                13
            ],
            "area": 221
        },
        {
            "id": 29884,
            "image_id": 39,
            "iscrowd": 0,
            "segmentation": [],
            "category_id": 3,
            "bbox": [
                597,
                294,
                6,
                9
            ],
            "area": 54
        },
        {
            "id": 29885,
            "image_id": 39,
            "iscrowd": 0,
            "segmentation": [],
            "category_id": 3,
            "bbox": [
                608,
                296,
                12,
                13
            ],
            "area": 156
        },
        {
            "id": 29886,
            "image_id": 39,
            "iscrowd": 0,
            "segmentation": [],
            "category_id": 3,
            "bbox": [
                624,
                296,
                9,
                13
            ],
            "area": 117
        },
        {
            "id": 29887,
            "image_id": 39,
            "iscrowd": 0,
            "segmentation": [],
            "category_id": 3,
            "bbox": [
                643,
                294,
                14,
                15
            ],
            "area": 210
        },
        {
            "id": 29888,
            "image_id": 39,
            "iscrowd": 0,
            "segmentation": [],
            "category_id": 3,
            "bbox": [
                679,
                294,
                55,
                15
            ],
            "area": 825
        },
        {
            "id": 29889,
            "image_id": 39,
            "iscrowd": 0,
            "segmentation": [],
            "category_id": 3,
            "bbox": [
                736,
                296,
                13,
                13
            ],
            "area": 169
        },
        {
            "id": 29890,
            "image_id": 39,
            "iscrowd": 0,
            "segmentation": [],
            "category_id": 3,
            "bbox": [
                752,
                296,
                20,
                13
            ],
            "area": 260
        },
        {
            "id": 29891,
            "image_id": 39,
            "iscrowd": 0,
            "segmentation": [],
            "category_id": 3,
            "bbox": [
                792,
                296,
                45,
                13
            ],
            "area": 585
        },
        {
            "id": 29892,
            "image_id": 39,
            "iscrowd": 0,
            "segmentation": [],
            "category_id": 3,
            "bbox": [
                212,
                310,
                4,
                10
            ],
            "area": 40
        },
        {
            "id": 29893,
            "image_id": 39,
            "iscrowd": 0,
            "segmentation": [],
            "category_id": 3,
            "bbox": [
                182,
                315,
                30,
                8
            ],
            "area": 240
        },
        {
            "id": 29894,
            "image_id": 39,
            "iscrowd": 0,
            "segmentation": [],
            "category_id": 7,
            "bbox": [
                478,
                348,
                10,
                16
            ],
            "area": 160
        },
        {
            "id": 29895,
            "image_id": 39,
            "iscrowd": 0,
            "segmentation": [],
            "category_id": 7,
            "bbox": [
                495,
                348,
                4,
                11
            ],
            "area": 44
        },
        {
            "id": 29896,
            "image_id": 39,
            "iscrowd": 0,
            "segmentation": [],
            "category_id": 7,
            "bbox": [
                604,
                347,
                13,
                22
            ],
            "area": 286
        },
        {
            "id": 29897,
            "image_id": 39,
            "iscrowd": 0,
            "segmentation": [],
            "category_id": 7,
            "bbox": [
                654,
                348,
                10,
                16
            ],
            "area": 160
        },
        {
            "id": 29898,
            "image_id": 39,
            "iscrowd": 0,
            "segmentation": [],
            "category_id": 7,
            "bbox": [
                766,
                347,
                13,
                22
            ],
            "area": 286
        },
        {
            "id": 29899,
            "image_id": 39,
            "iscrowd": 0,
            "segmentation": [],
            "category_id": 7,
            "bbox": [
                815,
                348,
                10,
                16
            ],
            "area": 160
        },
        {
            "id": 29900,
            "image_id": 39,
            "iscrowd": 0,
            "segmentation": [],
            "category_id": 7,
            "bbox": [
                186,
                356,
                37,
                13
            ],
            "area": 481
        },
        {
            "id": 29901,
            "image_id": 39,
            "iscrowd": 0,
            "segmentation": [],
            "category_id": 7,
            "bbox": [
                228,
                356,
                18,
                13
            ],
            "area": 234
        },
        {
            "id": 29902,
            "image_id": 39,
            "iscrowd": 0,
            "segmentation": [],
            "category_id": 7,
            "bbox": [
                251,
                356,
                29,
                13
            ],
            "area": 377
        },
        {
            "id": 29903,
            "image_id": 39,
            "iscrowd": 0,
            "segmentation": [],
            "category_id": 7,
            "bbox": [
                285,
                356,
                22,
                13
            ],
            "area": 286
        },
        {
            "id": 29904,
            "image_id": 39,
            "iscrowd": 0,
            "segmentation": [],
            "category_id": 7,
            "bbox": [
                312,
                356,
                34,
                13
            ],
            "area": 442
        },
        {
            "id": 29905,
            "image_id": 39,
            "iscrowd": 0,
            "segmentation": [],
            "category_id": 7,
            "bbox": [
                351,
                356,
                5,
                13
            ],
            "area": 65
        },
        {
            "id": 29906,
            "image_id": 39,
            "iscrowd": 0,
            "segmentation": [],
            "category_id": 7,
            "bbox": [
                361,
                356,
                33,
                13
            ],
            "area": 429
        },
        {
            "id": 29907,
            "image_id": 39,
            "iscrowd": 0,
            "segmentation": [],
            "category_id": 7,
            "bbox": [
                398,
                356,
                13,
                13
            ],
            "area": 169
        },
        {
            "id": 29908,
            "image_id": 39,
            "iscrowd": 0,
            "segmentation": [],
            "category_id": 7,
            "bbox": [
                416,
                353,
                62,
                16
            ],
            "area": 992
        },
        {
            "id": 29909,
            "image_id": 39,
            "iscrowd": 0,
            "segmentation": [],
            "category_id": 7,
            "bbox": [
                488,
                355,
                7,
                9
            ],
            "area": 63
        },
        {
            "id": 29910,
            "image_id": 39,
            "iscrowd": 0,
            "segmentation": [],
            "category_id": 7,
            "bbox": [
                501,
                356,
                4,
                13
            ],
            "area": 52
        },
        {
            "id": 29911,
            "image_id": 39,
            "iscrowd": 0,
            "segmentation": [],
            "category_id": 7,
            "bbox": [
                512,
                356,
                75,
                13
            ],
            "area": 975
        },
        {
            "id": 29912,
            "image_id": 39,
            "iscrowd": 0,
            "segmentation": [],
            "category_id": 7,
            "bbox": [
                592,
                356,
                9,
                13
            ],
            "area": 117
        },
        {
            "id": 29913,
            "image_id": 39,
            "iscrowd": 0,
            "segmentation": [],
            "category_id": 7,
            "bbox": [
                621,
                355,
                33,
                14
            ],
            "area": 462
        },
        {
            "id": 29914,
            "image_id": 39,
            "iscrowd": 0,
            "segmentation": [],
            "category_id": 7,
            "bbox": [
                664,
                355,
                12,
                14
            ],
            "area": 168
        },
        {
            "id": 29915,
            "image_id": 39,
            "iscrowd": 0,
            "segmentation": [],
            "category_id": 7,
            "bbox": [
                681,
                356,
                65,
                13
            ],
            "area": 845
        },
        {
            "id": 29916,
            "image_id": 39,
            "iscrowd": 0,
            "segmentation": [],
            "category_id": 7,
            "bbox": [
                750,
                356,
                15,
                13
            ],
            "area": 195
        },
        {
            "id": 29917,
            "image_id": 39,
            "iscrowd": 0,
            "segmentation": [],
            "category_id": 7,
            "bbox": [
                781,
                355,
                34,
                14
            ],
            "area": 476
        },
        {
            "id": 29918,
            "image_id": 39,
            "iscrowd": 0,
            "segmentation": [],
            "category_id": 7,
            "bbox": [
                825,
                355,
                12,
                14
            ],
            "area": 168
        },
        {
            "id": 29919,
            "image_id": 39,
            "iscrowd": 0,
            "segmentation": [],
            "category_id": 7,
            "bbox": [
                162,
                377,
                26,
                13
            ],
            "area": 338
        },
        {
            "id": 29920,
            "image_id": 39,
            "iscrowd": 0,
            "segmentation": [],
            "category_id": 7,
            "bbox": [
                193,
                377,
                38,
                13
            ],
            "area": 494
        },
        {
            "id": 29921,
            "image_id": 39,
            "iscrowd": 0,
            "segmentation": [],
            "category_id": 7,
            "bbox": [
                236,
                377,
                41,
                13
            ],
            "area": 533
        },
        {
            "id": 29922,
            "image_id": 39,
            "iscrowd": 0,
            "segmentation": [],
            "category_id": 7,
            "bbox": [
                283,
                377,
                18,
                13
            ],
            "area": 234
        },
        {
            "id": 29923,
            "image_id": 39,
            "iscrowd": 0,
            "segmentation": [],
            "category_id": 7,
            "bbox": [
                307,
                377,
                45,
                13
            ],
            "area": 585
        },
        {
            "id": 29924,
            "image_id": 39,
            "iscrowd": 0,
            "segmentation": [],
            "category_id": 3,
            "bbox": [
                461,
                390,
                12,
                47
            ],
            "area": 564
        },
        {
            "id": 29925,
            "image_id": 39,
            "iscrowd": 0,
            "segmentation": [],
            "category_id": 3,
            "bbox": [
                751,
                390,
                12,
                47
            ],
            "area": 564
        },
        {
            "id": 29926,
            "image_id": 39,
            "iscrowd": 0,
            "segmentation": [],
            "category_id": 3,
            "bbox": [
                195,
                396,
                23,
                47
            ],
            "area": 1081
        },
        {
            "id": 29927,
            "image_id": 39,
            "iscrowd": 0,
            "segmentation": [],
            "category_id": 3,
            "bbox": [
                765,
                396,
                21,
                47
            ],
            "area": 987
        },
        {
            "id": 29928,
            "image_id": 39,
            "iscrowd": 0,
            "segmentation": [],
            "category_id": 3,
            "bbox": [
                509,
                420,
                13,
                21
            ],
            "area": 273
        },
        {
            "id": 29929,
            "image_id": 39,
            "iscrowd": 0,
            "segmentation": [],
            "category_id": 3,
            "bbox": [
                570,
                420,
                12,
                21
            ],
            "area": 252
        },
        {
            "id": 29930,
            "image_id": 39,
            "iscrowd": 0,
            "segmentation": [],
            "category_id": 3,
            "bbox": [
                668,
                420,
                13,
                21
            ],
            "area": 273
        },
        {
            "id": 29931,
            "image_id": 39,
            "iscrowd": 0,
            "segmentation": [],
            "category_id": 3,
            "bbox": [
                225,
                428,
                12,
                22
            ],
            "area": 264
        },
        {
            "id": 29932,
            "image_id": 39,
            "iscrowd": 0,
            "segmentation": [],
            "category_id": 3,
            "bbox": [
                277,
                429,
                3,
                11
            ],
            "area": 33
        },
        {
            "id": 29933,
            "image_id": 39,
            "iscrowd": 0,
            "segmentation": [],
            "category_id": 3,
            "bbox": [
                344,
                429,
                10,
                15
            ],
            "area": 150
        },
        {
            "id": 29934,
            "image_id": 39,
            "iscrowd": 0,
            "segmentation": [],
            "category_id": 3,
            "bbox": [
                362,
                429,
                3,
                11
            ],
            "area": 33
        },
        {
            "id": 29935,
            "image_id": 39,
            "iscrowd": 0,
            "segmentation": [],
            "category_id": 3,
            "bbox": [
                375,
                429,
                11,
                15
            ],
            "area": 165
        },
        {
            "id": 29936,
            "image_id": 39,
            "iscrowd": 0,
            "segmentation": [],
            "category_id": 3,
            "bbox": [
                435,
                429,
                3,
                11
            ],
            "area": 33
        },
        {
            "id": 29937,
            "image_id": 39,
            "iscrowd": 0,
            "segmentation": [],
            "category_id": 3,
            "bbox": [
                522,
                429,
                13,
                12
            ],
            "area": 156
        },
        {
            "id": 29938,
            "image_id": 39,
            "iscrowd": 0,
            "segmentation": [],
            "category_id": 3,
            "bbox": [
                543,
                429,
                22,
                12
            ],
            "area": 264
        },
        {
            "id": 29939,
            "image_id": 39,
            "iscrowd": 0,
            "segmentation": [],
            "category_id": 3,
            "bbox": [
                586,
                429,
                21,
                12
            ],
            "area": 252
        },
        {
            "id": 29940,
            "image_id": 39,
            "iscrowd": 0,
            "segmentation": [],
            "category_id": 3,
            "bbox": [
                610,
                429,
                54,
                12
            ],
            "area": 648
        },
        {
            "id": 29941,
            "image_id": 39,
            "iscrowd": 0,
            "segmentation": [],
            "category_id": 3,
            "bbox": [
                685,
                427,
                29,
                14
            ],
            "area": 406
        },
        {
            "id": 29942,
            "image_id": 39,
            "iscrowd": 0,
            "segmentation": [],
            "category_id": 3,
            "bbox": [
                855,
                429,
                8,
                12
            ],
            "area": 96
        },
        {
            "id": 29943,
            "image_id": 39,
            "iscrowd": 0,
            "segmentation": [],
            "category_id": 3,
            "bbox": [
                162,
                437,
                30,
                20
            ],
            "area": 600
        },
        {
            "id": 29944,
            "image_id": 39,
            "iscrowd": 0,
            "segmentation": [],
            "category_id": 3,
            "bbox": [
                195,
                437,
                30,
                29
            ],
            "area": 870
        },
        {
            "id": 29945,
            "image_id": 39,
            "iscrowd": 0,
            "segmentation": [],
            "category_id": 3,
            "bbox": [
                237,
                433,
                39,
                17
            ],
            "area": 663
        },
        {
            "id": 29946,
            "image_id": 39,
            "iscrowd": 0,
            "segmentation": [],
            "category_id": 3,
            "bbox": [
                282,
                433,
                62,
                17
            ],
            "area": 1054
        },
        {
            "id": 29947,
            "image_id": 39,
            "iscrowd": 0,
            "segmentation": [],
            "category_id": 3,
            "bbox": [
                354,
                435,
                7,
                9
            ],
            "area": 63
        },
        {
            "id": 29948,
            "image_id": 39,
            "iscrowd": 0,
            "segmentation": [],
            "category_id": 3,
            "bbox": [
                367,
                437,
                8,
                13
            ],
            "area": 104
        },
        {
            "id": 29949,
            "image_id": 39,
            "iscrowd": 0,
            "segmentation": [],
            "category_id": 3,
            "bbox": [
                386,
                433,
                48,
                17
            ],
            "area": 816
        },
        {
            "id": 29950,
            "image_id": 39,
            "iscrowd": 0,
            "segmentation": [],
            "category_id": 3,
            "bbox": [
                444,
                437,
                13,
                13
            ],
            "area": 169
        },
        {
            "id": 29951,
            "image_id": 39,
            "iscrowd": 0,
            "segmentation": [],
            "category_id": 3,
            "bbox": [
                475,
                434,
                97,
                26
            ],
            "area": 2522
        },
        {
            "id": 29952,
            "image_id": 39,
            "iscrowd": 0,
            "segmentation": [],
            "category_id": 3,
            "bbox": [
                576,
                437,
                13,
                22
            ],
            "area": 286
        },
        {
            "id": 29953,
            "image_id": 39,
            "iscrowd": 0,
            "segmentation": [],
            "category_id": 3,
            "bbox": [
                593,
                446,
                21,
                13
            ],
            "area": 273
        },
        {
            "id": 29954,
            "image_id": 39,
            "iscrowd": 0,
            "segmentation": [],
            "category_id": 3,
            "bbox": [
                616,
                446,
                73,
                13
            ],
            "area": 949
        },
        {
            "id": 29955,
            "image_id": 39,
            "iscrowd": 0,
            "segmentation": [],
            "category_id": 3,
            "bbox": [
                694,
                437,
                13,
                22
            ],
            "area": 286
        },
        {
            "id": 29956,
            "image_id": 39,
            "iscrowd": 0,
            "segmentation": [],
            "category_id": 3,
            "bbox": [
                710,
                446,
                21,
                13
            ],
            "area": 273
        },
        {
            "id": 29957,
            "image_id": 39,
            "iscrowd": 0,
            "segmentation": [],
            "category_id": 3,
            "bbox": [
                734,
                446,
                15,
                13
            ],
            "area": 195
        },
        {
            "id": 29958,
            "image_id": 39,
            "iscrowd": 0,
            "segmentation": [],
            "category_id": 3,
            "bbox": [
                766,
                450,
                18,
                14
            ],
            "area": 252
        },
        {
            "id": 29959,
            "image_id": 39,
            "iscrowd": 0,
            "segmentation": [],
            "category_id": 3,
            "bbox": [
                791,
                448,
                14,
                12
            ],
            "area": 168
        },
        {
            "id": 29960,
            "image_id": 39,
            "iscrowd": 0,
            "segmentation": [],
            "category_id": 3,
            "bbox": [
                809,
                439,
                12,
                21
            ],
            "area": 252
        },
        {
            "id": 29961,
            "image_id": 39,
            "iscrowd": 0,
            "segmentation": [],
            "category_id": 3,
            "bbox": [
                825,
                442,
                102,
                18
            ],
            "area": 1836
        },
        {
            "id": 29962,
            "image_id": 39,
            "iscrowd": 0,
            "segmentation": [],
            "category_id": 3,
            "bbox": [
                792,
                474,
                45,
                12
            ],
            "area": 540
        },
        {
            "id": 29963,
            "image_id": 39,
            "iscrowd": 0,
            "segmentation": [],
            "category_id": 7,
            "bbox": [
                344,
                500,
                24,
                47
            ],
            "area": 1128
        },
        {
            "id": 29964,
            "image_id": 39,
            "iscrowd": 0,
            "segmentation": [],
            "category_id": 7,
            "bbox": [
                186,
                520,
                42,
                13
            ],
            "area": 546
        },
        {
            "id": 29965,
            "image_id": 39,
            "iscrowd": 0,
            "segmentation": [],
            "category_id": 7,
            "bbox": [
                233,
                520,
                19,
                13
            ],
            "area": 247
        },
        {
            "id": 29966,
            "image_id": 39,
            "iscrowd": 0,
            "segmentation": [],
            "category_id": 7,
            "bbox": [
                257,
                520,
                42,
                13
            ],
            "area": 546
        },
        {
            "id": 29967,
            "image_id": 39,
            "iscrowd": 0,
            "segmentation": [],
            "category_id": 7,
            "bbox": [
                434,
                533,
                4,
                15
            ],
            "area": 60
        },
        {
            "id": 29968,
            "image_id": 39,
            "iscrowd": 0,
            "segmentation": [],
            "category_id": 7,
            "bbox": [
                474,
                533,
                4,
                10
            ],
            "area": 40
        },
        {
            "id": 29969,
            "image_id": 39,
            "iscrowd": 0,
            "segmentation": [],
            "category_id": 7,
            "bbox": [
                552,
                533,
                10,
                15
            ],
            "area": 150
        },
        {
            "id": 29970,
            "image_id": 39,
            "iscrowd": 0,
            "segmentation": [],
            "category_id": 7,
            "bbox": [
                629,
                532,
                12,
                22
            ],
            "area": 264
        },
        {
            "id": 29971,
            "image_id": 39,
            "iscrowd": 0,
            "segmentation": [],
            "category_id": 7,
            "bbox": [
                370,
                538,
                54,
                16
            ],
            "area": 864
        },
        {
            "id": 29972,
            "image_id": 39,
            "iscrowd": 0,
            "segmentation": [],
            "category_id": 7,
            "bbox": [
                427,
                541,
                7,
                13
            ],
            "area": 91
        },
        {
            "id": 29973,
            "image_id": 39,
            "iscrowd": 0,
            "segmentation": [],
            "category_id": 7,
            "bbox": [
                438,
                539,
                36,
                15
            ],
            "area": 540
        },
        {
            "id": 29974,
            "image_id": 39,
            "iscrowd": 0,
            "segmentation": [],
            "category_id": 7,
            "bbox": [
                484,
                541,
                13,
                13
            ],
            "area": 169
        },
        {
            "id": 29975,
            "image_id": 39,
            "iscrowd": 0,
            "segmentation": [],
            "category_id": 7,
            "bbox": [
                501,
                539,
                51,
                15
            ],
            "area": 765
        },
        {
            "id": 29976,
            "image_id": 39,
            "iscrowd": 0,
            "segmentation": [],
            "category_id": 7,
            "bbox": [
                562,
                539,
                29,
                15
            ],
            "area": 435
        },
        {
            "id": 29977,
            "image_id": 39,
            "iscrowd": 0,
            "segmentation": [],
            "category_id": 7,
            "bbox": [
                594,
                541,
                13,
                13
            ],
            "area": 169
        },
        {
            "id": 29978,
            "image_id": 39,
            "iscrowd": 0,
            "segmentation": [],
            "category_id": 7,
            "bbox": [
                609,
                541,
                16,
                13
            ],
            "area": 208
        },
        {
            "id": 29979,
            "image_id": 39,
            "iscrowd": 0,
            "segmentation": [],
            "category_id": 7,
            "bbox": [
                645,
                541,
                13,
                13
            ],
            "area": 169
        },
        {
            "id": 29980,
            "image_id": 39,
            "iscrowd": 0,
            "segmentation": [],
            "category_id": 7,
            "bbox": [
                792,
                541,
                45,
                13
            ],
            "area": 585
        },
        {
            "id": 29981,
            "image_id": 39,
            "iscrowd": 0,
            "segmentation": [],
            "category_id": 7,
            "bbox": [
                361,
                554,
                4,
                11
            ],
            "area": 44
        },
        {
            "id": 29982,
            "image_id": 39,
            "iscrowd": 0,
            "segmentation": [],
            "category_id": 7,
            "bbox": [
                346,
                559,
                15,
                9
            ],
            "area": 135
        },
        {
            "id": 29983,
            "image_id": 39,
            "iscrowd": 0,
            "segmentation": [],
            "category_id": 7,
            "bbox": [
                446,
                572,
                13,
                22
            ],
            "area": 286
        },
        {
            "id": 29984,
            "image_id": 39,
            "iscrowd": 0,
            "segmentation": [],
            "category_id": 7,
            "bbox": [
                481,
                573,
                10,
                16
            ],
            "area": 160
        },
        {
            "id": 29985,
            "image_id": 39,
            "iscrowd": 0,
            "segmentation": [],
            "category_id": 7,
            "bbox": [
                162,
                581,
                50,
                13
            ],
            "area": 650
        },
        {
            "id": 29986,
            "image_id": 39,
            "iscrowd": 0,
            "segmentation": [],
            "category_id": 7,
            "bbox": [
                217,
                581,
                19,
                13
            ],
            "area": 247
        },
        {
            "id": 29987,
            "image_id": 39,
            "iscrowd": 0,
            "segmentation": [],
            "category_id": 7,
            "bbox": [
                241,
                581,
                50,
                13
            ],
            "area": 650
        },
        {
            "id": 29988,
            "image_id": 39,
            "iscrowd": 0,
            "segmentation": [],
            "category_id": 7,
            "bbox": [
                296,
                581,
                45,
                13
            ],
            "area": 585
        },
        {
            "id": 29989,
            "image_id": 39,
            "iscrowd": 0,
            "segmentation": [],
            "category_id": 7,
            "bbox": [
                347,
                581,
                17,
                13
            ],
            "area": 221
        },
        {
            "id": 29990,
            "image_id": 39,
            "iscrowd": 0,
            "segmentation": [],
            "category_id": 7,
            "bbox": [
                369,
                581,
                56,
                13
            ],
            "area": 728
        },
        {
            "id": 29991,
            "image_id": 39,
            "iscrowd": 0,
            "segmentation": [],
            "category_id": 7,
            "bbox": [
                431,
                581,
                10,
                13
            ],
            "area": 130
        },
        {
            "id": 29992,
            "image_id": 39,
            "iscrowd": 0,
            "segmentation": [],
            "category_id": 7,
            "bbox": [
                463,
                581,
                17,
                13
            ],
            "area": 221
        },
        {
            "id": 29993,
            "image_id": 39,
            "iscrowd": 0,
            "segmentation": [],
            "category_id": 7,
            "bbox": [
                491,
                580,
                7,
                9
            ],
            "area": 63
        },
        {
            "id": 29994,
            "image_id": 39,
            "iscrowd": 0,
            "segmentation": [],
            "category_id": 7,
            "bbox": [
                504,
                581,
                14,
                13
            ],
            "area": 182
        },
        {
            "id": 29995,
            "image_id": 39,
            "iscrowd": 0,
            "segmentation": [],
            "category_id": 7,
            "bbox": [
                524,
                581,
                21,
                13
            ],
            "area": 273
        },
        {
            "id": 29996,
            "image_id": 39,
            "iscrowd": 0,
            "segmentation": [],
            "category_id": 3,
            "bbox": [
                459,
                593,
                13,
                46
            ],
            "area": 598
        },
        {
            "id": 29997,
            "image_id": 39,
            "iscrowd": 0,
            "segmentation": [],
            "category_id": 3,
            "bbox": [
                831,
                593,
                13,
                46
            ],
            "area": 598
        },
        {
            "id": 29998,
            "image_id": 39,
            "iscrowd": 0,
            "segmentation": [],
            "category_id": 3,
            "bbox": [
                195,
                602,
                23,
                47
            ],
            "area": 1081
        },
        {
            "id": 29999,
            "image_id": 39,
            "iscrowd": 0,
            "segmentation": [],
            "category_id": 3,
            "bbox": [
                474,
                602,
                20,
                47
            ],
            "area": 940
        },
        {
            "id": 30000,
            "image_id": 39,
            "iscrowd": 0,
            "segmentation": [],
            "category_id": 3,
            "bbox": [
                478,
                624,
                13,
                15
            ],
            "area": 195
        },
        {
            "id": 30001,
            "image_id": 39,
            "iscrowd": 0,
            "segmentation": [],
            "category_id": 3,
            "bbox": [
                519,
                626,
                13,
                21
            ],
            "area": 273
        },
        {
            "id": 30002,
            "image_id": 39,
            "iscrowd": 0,
            "segmentation": [],
            "category_id": 3,
            "bbox": [
                611,
                626,
                13,
                21
            ],
            "area": 273
        },
        {
            "id": 30003,
            "image_id": 39,
            "iscrowd": 0,
            "segmentation": [],
            "category_id": 3,
            "bbox": [
                646,
                627,
                10,
                15
            ],
            "area": 150
        },
        {
            "id": 30004,
            "image_id": 39,
            "iscrowd": 0,
            "segmentation": [],
            "category_id": 3,
            "bbox": [
                687,
                627,
                10,
                15
            ],
            "area": 150
        },
        {
            "id": 30005,
            "image_id": 39,
            "iscrowd": 0,
            "segmentation": [],
            "category_id": 3,
            "bbox": [
                729,
                626,
                13,
                21
            ],
            "area": 273
        },
        {
            "id": 30006,
            "image_id": 39,
            "iscrowd": 0,
            "segmentation": [],
            "category_id": 3,
            "bbox": [
                805,
                627,
                10,
                15
            ],
            "area": 150
        },
        {
            "id": 30007,
            "image_id": 39,
            "iscrowd": 0,
            "segmentation": [],
            "category_id": 3,
            "bbox": [
                225,
                634,
                12,
                22
            ],
            "area": 264
        },
        {
            "id": 30008,
            "image_id": 39,
            "iscrowd": 0,
            "segmentation": [],
            "category_id": 3,
            "bbox": [
                277,
                635,
                3,
                11
            ],
            "area": 33
        },
        {
            "id": 30009,
            "image_id": 39,
            "iscrowd": 0,
            "segmentation": [],
            "category_id": 3,
            "bbox": [
                344,
                635,
                10,
                15
            ],
            "area": 150
        },
        {
            "id": 30010,
            "image_id": 39,
            "iscrowd": 0,
            "segmentation": [],
            "category_id": 3,
            "bbox": [
                362,
                635,
                3,
                11
            ],
            "area": 33
        },
        {
            "id": 30011,
            "image_id": 39,
            "iscrowd": 0,
            "segmentation": [],
            "category_id": 3,
            "bbox": [
                402,
                635,
                4,
                11
            ],
            "area": 44
        },
        {
            "id": 30012,
            "image_id": 39,
            "iscrowd": 0,
            "segmentation": [],
            "category_id": 3,
            "bbox": [
                429,
                634,
                25,
                22
            ],
            "area": 550
        },
        {
            "id": 30013,
            "image_id": 39,
            "iscrowd": 0,
            "segmentation": [],
            "category_id": 3,
            "bbox": [
                501,
                635,
                14,
                12
            ],
            "area": 168
        },
        {
            "id": 30014,
            "image_id": 39,
            "iscrowd": 0,
            "segmentation": [],
            "category_id": 3,
            "bbox": [
                535,
                633,
                72,
                14
            ],
            "area": 1008
        },
        {
            "id": 30015,
            "image_id": 39,
            "iscrowd": 0,
            "segmentation": [],
            "category_id": 3,
            "bbox": [
                627,
                633,
                19,
                14
            ],
            "area": 266
        },
        {
            "id": 30016,
            "image_id": 39,
            "iscrowd": 0,
            "segmentation": [],
            "category_id": 3,
            "bbox": [
                656,
                633,
                31,
                14
            ],
            "area": 434
        },
        {
            "id": 30017,
            "image_id": 39,
            "iscrowd": 0,
            "segmentation": [],
            "category_id": 3,
            "bbox": [
                697,
                633,
                28,
                14
            ],
            "area": 392
        },
        {
            "id": 30018,
            "image_id": 39,
            "iscrowd": 0,
            "segmentation": [],
            "category_id": 3,
            "bbox": [
                745,
                633,
                60,
                14
            ],
            "area": 840
        },
        {
            "id": 30019,
            "image_id": 39,
            "iscrowd": 0,
            "segmentation": [],
            "category_id": 3,
            "bbox": [
                815,
                633,
                14,
                14
            ],
            "area": 196
        },
        {
            "id": 30020,
            "image_id": 39,
            "iscrowd": 0,
            "segmentation": [],
            "category_id": 3,
            "bbox": [
                162,
                643,
                30,
                20
            ],
            "area": 600
        },
        {
            "id": 30021,
            "image_id": 39,
            "iscrowd": 0,
            "segmentation": [],
            "category_id": 3,
            "bbox": [
                218,
                643,
                7,
                13
            ],
            "area": 91
        },
        {
            "id": 30022,
            "image_id": 39,
            "iscrowd": 0,
            "segmentation": [],
            "category_id": 3,
            "bbox": [
                237,
                639,
                39,
                17
            ],
            "area": 663
        },
        {
            "id": 30023,
            "image_id": 39,
            "iscrowd": 0,
            "segmentation": [],
            "category_id": 3,
            "bbox": [
                282,
                639,
                62,
                17
            ],
            "area": 1054
        },
        {
            "id": 30024,
            "image_id": 39,
            "iscrowd": 0,
            "segmentation": [],
            "category_id": 3,
            "bbox": [
                354,
                641,
                7,
                9
            ],
            "area": 63
        },
        {
            "id": 30025,
            "image_id": 39,
            "iscrowd": 0,
            "segmentation": [],
            "category_id": 3,
            "bbox": [
                367,
                641,
                35,
                15
            ],
            "area": 525
        },
        {
            "id": 30026,
            "image_id": 39,
            "iscrowd": 0,
            "segmentation": [],
            "category_id": 3,
            "bbox": [
                412,
                643,
                13,
                13
            ],
            "area": 169
        },
        {
            "id": 30027,
            "image_id": 39,
            "iscrowd": 0,
            "segmentation": [],
            "category_id": 3,
            "bbox": [
                444,
                652,
                10,
                13
            ],
            "area": 130
        },
        {
            "id": 30028,
            "image_id": 39,
            "iscrowd": 0,
            "segmentation": [],
            "category_id": 3,
            "bbox": [
                470,
                640,
                35,
                60
            ],
            "area": 2100
        },
        {
            "id": 30029,
            "image_id": 39,
            "iscrowd": 0,
            "segmentation": [],
            "category_id": 3,
            "bbox": [
                548,
                652,
                14,
                13
            ],
            "area": 182
        },
        {
            "id": 30030,
            "image_id": 39,
            "iscrowd": 0,
            "segmentation": [],
            "category_id": 3,
            "bbox": [
                566,
                652,
                13,
                13
            ],
            "area": 169
        },
        {
            "id": 30031,
            "image_id": 39,
            "iscrowd": 0,
            "segmentation": [],
            "category_id": 3,
            "bbox": [
                582,
                645,
                106,
                20
            ],
            "area": 2120
        },
        {
            "id": 30032,
            "image_id": 39,
            "iscrowd": 0,
            "segmentation": [],
            "category_id": 3,
            "bbox": [
                691,
                652,
                13,
                13
            ],
            "area": 169
        },
        {
            "id": 30033,
            "image_id": 39,
            "iscrowd": 0,
            "segmentation": [],
            "category_id": 3,
            "bbox": [
                708,
                640,
                73,
                47
            ],
            "area": 3431
        },
        {
            "id": 30034,
            "image_id": 39,
            "iscrowd": 0,
            "segmentation": [],
            "category_id": 3,
            "bbox": [
                195,
                658,
                22,
                14
            ],
            "area": 308
        },
        {
            "id": 30035,
            "image_id": 39,
            "iscrowd": 0,
            "segmentation": [],
            "category_id": 3,
            "bbox": [
                470,
                661,
                26,
                48
            ],
            "area": 1248
        },
        {
            "id": 30036,
            "image_id": 39,
            "iscrowd": 0,
            "segmentation": [],
            "category_id": 3,
            "bbox": [
                710,
                662,
                14,
                47
            ],
            "area": 658
        },
        {
            "id": 30037,
            "image_id": 39,
            "iscrowd": 0,
            "segmentation": [],
            "category_id": 3,
            "bbox": [
                605,
                686,
                8,
                12
            ],
            "area": 96
        },
        {
            "id": 30038,
            "image_id": 39,
            "iscrowd": 0,
            "segmentation": [],
            "category_id": 3,
            "bbox": [
                528,
                695,
                12,
                21
            ],
            "area": 252
        },
        {
            "id": 30039,
            "image_id": 39,
            "iscrowd": 0,
            "segmentation": [],
            "category_id": 3,
            "bbox": [
                550,
                695,
                13,
                21
            ],
            "area": 273
        },
        {
            "id": 30040,
            "image_id": 39,
            "iscrowd": 0,
            "segmentation": [],
            "category_id": 3,
            "bbox": [
                598,
                698,
                4,
                11
            ],
            "area": 44
        },
        {
            "id": 30041,
            "image_id": 39,
            "iscrowd": 0,
            "segmentation": [],
            "category_id": 3,
            "bbox": [
                635,
                698,
                4,
                11
            ],
            "area": 44
        },
        {
            "id": 30042,
            "image_id": 39,
            "iscrowd": 0,
            "segmentation": [],
            "category_id": 3,
            "bbox": [
                698,
                698,
                3,
                11
            ],
            "area": 33
        },
        {
            "id": 30043,
            "image_id": 39,
            "iscrowd": 0,
            "segmentation": [],
            "category_id": 3,
            "bbox": [
                727,
                694,
                4,
                13
            ],
            "area": 52
        },
        {
            "id": 30044,
            "image_id": 39,
            "iscrowd": 0,
            "segmentation": [],
            "category_id": 3,
            "bbox": [
                792,
                694,
                45,
                13
            ],
            "area": 585
        },
        {
            "id": 30045,
            "image_id": 39,
            "iscrowd": 0,
            "segmentation": [],
            "category_id": 3,
            "bbox": [
                500,
                707,
                3,
                11
            ],
            "area": 33
        },
        {
            "id": 30046,
            "image_id": 39,
            "iscrowd": 0,
            "segmentation": [],
            "category_id": 3,
            "bbox": [
                510,
                704,
                14,
                12
            ],
            "area": 168
        },
        {
            "id": 30047,
            "image_id": 39,
            "iscrowd": 0,
            "segmentation": [],
            "category_id": 3,
            "bbox": [
                544,
                704,
                6,
                12
            ],
            "area": 72
        },
        {
            "id": 30048,
            "image_id": 39,
            "iscrowd": 0,
            "segmentation": [],
            "category_id": 3,
            "bbox": [
                563,
                703,
                35,
                13
            ],
            "area": 455
        },
        {
            "id": 30049,
            "image_id": 39,
            "iscrowd": 0,
            "segmentation": [],
            "category_id": 3,
            "bbox": [
                603,
                703,
                32,
                13
            ],
            "area": 416
        },
        {
            "id": 30050,
            "image_id": 39,
            "iscrowd": 0,
            "segmentation": [],
            "category_id": 3,
            "bbox": [
                640,
                703,
                58,
                13
            ],
            "area": 754
        },
        {
            "id": 30051,
            "image_id": 39,
            "iscrowd": 0,
            "segmentation": [],
            "category_id": 3,
            "bbox": [
                702,
                703,
                5,
                9
            ],
            "area": 45
        },
        {
            "id": 30052,
            "image_id": 39,
            "iscrowd": 0,
            "segmentation": [],
            "category_id": 3,
            "bbox": [
                485,
                713,
                15,
                8
            ],
            "area": 120
        },
        {
            "id": 30053,
            "image_id": 39,
            "iscrowd": 0,
            "segmentation": [],
            "category_id": 7,
            "bbox": [
                186,
                754,
                42,
                13
            ],
            "area": 546
        },
        {
            "id": 30054,
            "image_id": 39,
            "iscrowd": 0,
            "segmentation": [],
            "category_id": 7,
            "bbox": [
                233,
                754,
                19,
                13
            ],
            "area": 247
        },
        {
            "id": 30055,
            "image_id": 39,
            "iscrowd": 0,
            "segmentation": [],
            "category_id": 7,
            "bbox": [
                257,
                754,
                42,
                13
            ],
            "area": 546
        },
        {
            "id": 30056,
            "image_id": 39,
            "iscrowd": 0,
            "segmentation": [],
            "category_id": 3,
            "bbox": [
                267,
                773,
                24,
                47
            ],
            "area": 1128
        },
        {
            "id": 30057,
            "image_id": 39,
            "iscrowd": 0,
            "segmentation": [],
            "category_id": 3,
            "bbox": [
                357,
                805,
                4,
                16
            ],
            "area": 64
        },
        {
            "id": 30058,
            "image_id": 39,
            "iscrowd": 0,
            "segmentation": [],
            "category_id": 3,
            "bbox": [
                400,
                806,
                3,
                10
            ],
            "area": 30
        },
        {
            "id": 30059,
            "image_id": 39,
            "iscrowd": 0,
            "segmentation": [],
            "category_id": 3,
            "bbox": [
                514,
                805,
                10,
                16
            ],
            "area": 160
        },
        {
            "id": 30060,
            "image_id": 39,
            "iscrowd": 0,
            "segmentation": [],
            "category_id": 3,
            "bbox": [
                601,
                805,
                12,
                22
            ],
            "area": 264
        },
        {
            "id": 30061,
            "image_id": 39,
            "iscrowd": 0,
            "segmentation": [],
            "category_id": 3,
            "bbox": [
                630,
                805,
                12,
                22
            ],
            "area": 264
        },
        {
            "id": 30062,
            "image_id": 39,
            "iscrowd": 0,
            "segmentation": [],
            "category_id": 3,
            "bbox": [
                294,
                812,
                54,
                15
            ],
            "area": 810
        },
        {
            "id": 30063,
            "image_id": 39,
            "iscrowd": 0,
            "segmentation": [],
            "category_id": 3,
            "bbox": [
                350,
                814,
                7,
                13
            ],
            "area": 91
        },
        {
            "id": 30064,
            "image_id": 39,
            "iscrowd": 0,
            "segmentation": [],
            "category_id": 3,
            "bbox": [
                362,
                812,
                38,
                15
            ],
            "area": 570
        },
        {
            "id": 30065,
            "image_id": 39,
            "iscrowd": 0,
            "segmentation": [],
            "category_id": 3,
            "bbox": [
                409,
                814,
                13,
                13
            ],
            "area": 169
        },
        {
            "id": 30066,
            "image_id": 39,
            "iscrowd": 0,
            "segmentation": [],
            "category_id": 3,
            "bbox": [
                426,
                812,
                75,
                15
            ],
            "area": 1125
        },
        {
            "id": 30067,
            "image_id": 39,
            "iscrowd": 0,
            "segmentation": [],
            "category_id": 3,
            "bbox": [
                503,
                814,
                11,
                13
            ],
            "area": 143
        },
        {
            "id": 30068,
            "image_id": 39,
            "iscrowd": 0,
            "segmentation": [],
            "category_id": 3,
            "bbox": [
                524,
                812,
                55,
                15
            ],
            "area": 825
        },
        {
            "id": 30069,
            "image_id": 39,
            "iscrowd": 0,
            "segmentation": [],
            "category_id": 3,
            "bbox": [
                581,
                814,
                16,
                13
            ],
            "area": 208
        },
        {
            "id": 30070,
            "image_id": 39,
            "iscrowd": 0,
            "segmentation": [],
            "category_id": 3,
            "bbox": [
                617,
                814,
                8,
                13
            ],
            "area": 104
        },
        {
            "id": 30071,
            "image_id": 39,
            "iscrowd": 0,
            "segmentation": [],
            "category_id": 3,
            "bbox": [
                647,
                812,
                62,
                15
            ],
            "area": 930
        },
        {
            "id": 30072,
            "image_id": 39,
            "iscrowd": 0,
            "segmentation": [],
            "category_id": 3,
            "bbox": [
                711,
                814,
                21,
                13
            ],
            "area": 273
        },
        {
            "id": 30073,
            "image_id": 39,
            "iscrowd": 0,
            "segmentation": [],
            "category_id": 3,
            "bbox": [
                792,
                814,
                45,
                13
            ],
            "area": 585
        },
        {
            "id": 30074,
            "image_id": 39,
            "iscrowd": 0,
            "segmentation": [],
            "category_id": 3,
            "bbox": [
                284,
                827,
                4,
                11
            ],
            "area": 44
        },
        {
            "id": 30075,
            "image_id": 39,
            "iscrowd": 0,
            "segmentation": [],
            "category_id": 3,
            "bbox": [
                270,
                832,
                14,
                9
            ],
            "area": 126
        },
        {
            "id": 30076,
            "image_id": 39,
            "iscrowd": 0,
            "segmentation": [],
            "category_id": 7,
            "bbox": [
                491,
                897,
                17,
                14
            ],
            "area": 238
        },
        {
            "id": 30077,
            "image_id": 39,
            "iscrowd": 0,
            "segmentation": [],
            "category_id": 3,
            "bbox": [
                252,
                136,
                6,
                0
            ],
            "area": 0
        },
        {
            "id": 30078,
            "image_id": 39,
            "iscrowd": 0,
            "segmentation": [],
            "category_id": 3,
            "bbox": [
                488,
                140,
                152,
                0
            ],
            "area": 0
        },
        {
            "id": 30079,
            "image_id": 39,
            "iscrowd": 0,
            "segmentation": [],
            "category_id": 3,
            "bbox": [
                696,
                140,
                171,
                0
            ],
            "area": 0
        },
        {
            "id": 30080,
            "image_id": 39,
            "iscrowd": 0,
            "segmentation": [],
            "category_id": 3,
            "bbox": [
                475,
                444,
                274,
                0
            ],
            "area": 0
        },
        {
            "id": 30081,
            "image_id": 39,
            "iscrowd": 0,
            "segmentation": [],
            "category_id": 3,
            "bbox": [
                791,
                444,
                137,
                0
            ],
            "area": 0
        },
        {
            "id": 30082,
            "image_id": 39,
            "iscrowd": 0,
            "segmentation": [],
            "category_id": 3,
            "bbox": [
                444,
                650,
                10,
                0
            ],
            "area": 0
        },
        {
            "id": 30083,
            "image_id": 39,
            "iscrowd": 0,
            "segmentation": [],
            "category_id": 3,
            "bbox": [
                501,
                650,
                328,
                0
            ],
            "area": 0
        },
        {
            "id": 30084,
            "image_id": 39,
            "iscrowd": 0,
            "segmentation": [],
            "category_id": 3,
            "bbox": [
                510,
                701,
                198,
                0
            ],
            "area": 0
        }
    ]
}